MANIFEST.in
README.md
setup.py
version.py
src/periscope_daemon/__init__.py
src/periscope_daemon/periscope_daemon.py
src/periscope_daemon.egg-info/PKG-INFO
src/periscope_daemon.egg-info/SOURCES.txt
src/periscope_daemon.egg-info/dependency_links.txt
src/periscope_daemon.egg-info/entry_points.txt
src/periscope_daemon.egg-info/requires.txt
src/periscope_daemon.egg-info/top_level.txt
src/periscope_daemon/config/daemon.conf
src/periscope_daemon/config/logging.conf