Metadata-Version: 1.0
Name: periscope-daemon
Version: 0.0.6.dev
Summary: Python daemon to download automagically subtitles. Build on top of the great periscope (https://github.com/patrickdessalle/periscope)
Home-page: https://github.com/jcsaaddupuy/periscoped
Author: Jean-Christophe Saad-Dupuy
Author-email: saad.dupuy@gmail.com
License: WTFPL
Platform: UNKNOWN
